aiogram_fsm_storage/__init__.py
aiogram_fsm_storage/json_storage.py
aiogram_fsm_storage/pickle_storage.py
aiogram_fsm_storage/sqlite_storage.py
aiogram_fsm_storage-0.1.8.dist-info/licenses/LICENSE
aiogram_fsm_storage-0.1.8.dist-info/METADATA
aiogram_fsm_storage-0.1.8.dist-info/WHEEL
aiogram_fsm_storage-0.1.8.dist-info/top_level.txt
aiogram_fsm_storage-0.1.8.dist-info/RECORD
