Metadata-Version: 2.4
Name: aiogram-fsm-storage
Version: 0.1.8
Summary: Custom FSM storage backends for Aiogram v3
Author: Twix
License-Expression: MIT
Requires-Python: >=3.8
License-File: LICENSE
Requires-Dist: aiogram>=3.0.0
Requires-Dist: aiosqlite
Dynamic: license-file
